communication/__init__.py
communication/admin.py
communication/apps.py
communication/formsets.py
communication/models.py
communication/tests.py
communication/views.py
communication/configurations/__init__.py
communication/configurations/communication.py
communication/constants/__init__.py
communication/constants/communication_requests.py
communication/constants/communication_types.py
communication/constants/providers.py
communication/management/__init__.py
communication/management/commands/__init__.py
communication/management/commands/send_test_communications.py
communication/migrations/0001_initial.py
communication/migrations/__init__.py
communication/migrations/__pycache__/0001_initial.cpython-312.pyc
communication/migrations/__pycache__/__init__.cpython-312.pyc
communication/services/__init__.py
communication/services/email/__init__.py
communication/services/email/smtp.py
communication/utility/__init__.py
communication/utility/communication_types.py
communication/utility/configurations.py
django_communications/__init__.py
django_communications/asgi.py
django_communications/settings.py
django_communications/urls.py
django_communications/wsgi.py
django_communications-0.1.0.dist-info/METADATA
django_communications-0.1.0.dist-info/WHEEL
django_communications-0.1.0.dist-info/top_level.txt
django_communications-0.1.0.dist-info/RECORD
